MANIFEST.in
README.rst
setup.py
docs/HISTORY.txt
docs/LICENSE.GPL
docs/LICENSE.txt
ftw/__init__.py
ftw.showroom.egg-info/PKG-INFO
ftw.showroom.egg-info/SOURCES.txt
ftw.showroom.egg-info/dependency_links.txt
ftw.showroom.egg-info/entry_points.txt
ftw.showroom.egg-info/namespace_packages.txt
ftw.showroom.egg-info/not-zip-safe
ftw.showroom.egg-info/requires.txt
ftw.showroom.egg-info/top_level.txt
ftw/showroom/__init__.py
ftw/showroom/configure.zcml
ftw/showroom/testing.py
ftw/showroom/Extensions/__init__.py
ftw/showroom/Extensions/install.py
ftw/showroom/js/src/event.js
ftw/showroom/js/src/ftw.showroom.js
ftw/showroom/js/src/gallery.js
ftw/showroom/js/src/item.js
ftw/showroom/js/src/observer.js
ftw/showroom/js/src/register.js
ftw/showroom/js/src/utils.js
ftw/showroom/js/test/fixtures/append_list.html
ftw/showroom/js/test/fixtures/default_item.html
ftw/showroom/js/test/fixtures/default_list.html
ftw/showroom/js/test/fixtures/default_outlet.html
ftw/showroom/js/test/fixtures/dirty_item_list.html
ftw/showroom/js/test/fixtures/multiple_list.html
ftw/showroom/js/test/fixtures/prepend_list.html
ftw/showroom/js/test/fixtures/reference_item.html
ftw/showroom/js/test/helpers/builder.js
ftw/showroom/js/test/helpers/waitfor.js
ftw/showroom/js/test/spec/gallery.js
ftw/showroom/js/test/spec/item.js
ftw/showroom/js/test/spec/observer.js
ftw/showroom/js/test/spec/register.js
ftw/showroom/js/test/spec/showroom.js
ftw/showroom/js/test/spec/utils.js
ftw/showroom/profiles/default/cssregistry.xml
ftw/showroom/profiles/default/jsregistry.xml
ftw/showroom/profiles/default/metadata.xml
ftw/showroom/profiles/uninstall/cssregistry.xml
ftw/showroom/profiles/uninstall/jsregistry.xml
ftw/showroom/resources/ftw.showroom.js
ftw/showroom/resources/handlebars.js
ftw/showroom/resources/style.css
ftw/showroom/tests/__init__.py
ftw/showroom/tests/test_profile.py
ftw/showroom/tests/test_uninstall.py
ftw/showroom/upgrades/__init__.py
ftw/showroom/upgrades/20161019113902_use_ft_was_namespace/__init__.py
ftw/showroom/upgrades/20161019113902_use_ft_was_namespace/jsregistry.xml
ftw/showroom/upgrades/20161019113902_use_ft_was_namespace/upgrade.py