Metadata-Version: 1.1
Name: ftw.showroom
Version: 1.5.1
Summary: Javascript library to make gallery overlays
Home-page: https://github.com/4teamwork/ftw.showroom
Author: Kevin Bieri
Author-email: mailto:info@4teamwork.ch
License: GPL2
Keywords: ftw plone showroom
Platform: UNKNOWN
Classifier: Framework :: Plone
Classifier: Framework :: Plone :: 4.3
Classifier: License :: OSI Approved :: GNU General Public License (GPL)
Classifier: Programming Language :: Python
Classifier: Programming Language :: Python :: 2.7
Classifier: Topic :: Software Development :: Libraries :: Python Modules
